cfs_ros/__init__.py
cfs_ros/cfs_service.py
cfs_ros/juliapkg.json
cfs_ros/main.py
cfs_ros-0.0.1.dist-info/METADATA
cfs_ros-0.0.1.dist-info/WHEEL
cfs_ros-0.0.1.dist-info/entry_points.txt
cfs_ros-0.0.1.dist-info/top_level.txt
cfs_ros-0.0.1.dist-info/RECORD
