Metadata-Version: 2.2
Name: cfs-ros
Version: 0.0.1
Summary: CFS Planner for ROS
Author-email: Bo <bobobobosu@gmail.com>
Maintainer-email: Bo <bobobobosu@gmail.com>
Keywords: ros,planning
Requires-Python: >=3.8
Requires-Dist: juliacall
Requires-Dist: juliapkg
Requires-Dist: numpy
